<?xml version="1.0" encoding="utf-8"?>
<!--Autogenerated by CreoleToXMLSchema!-->
<database name="workflow">
  <table name="PM_REPORT">
    <vendor type="mysql">
      <parameter name="Name" value="PM_REPORT"/>
      <parameter name="Engine" value="MyISAM"/>
      <parameter name="Version" value="10"/>
      <parameter name="Row_format" value="Dynamic"/>
      <parameter name="Auto_increment" value=""/>
      <parameter name="Collation" value="utf8_general_ci"/>
      <parameter name="Create_options" value=""/>
      <parameter name="Comment" value="The plugin demo table for pmReports"/>
    </vendor>
    <column name="PMR_UID" type="VARCHAR" size="32" required="true" primaryKey="true" default="">
      <vendor type="mysql">
        <parameter name="Field" value="PMR_UID"/>
        <parameter name="Type" value="varchar(32)"/>
        <parameter name="Null" value="NO"/>
        <parameter name="Key" value="PRI"/>
        <parameter name="Default" value=""/>
        <parameter name="Extra" value=""/>
      </vendor>
    </column>
    <column name="DYN_UID" type="VARCHAR" size="32" required="true" default="">
      <vendor type="mysql">
        <parameter name="Field" value="DYN_UID"/>
        <parameter name="Type" value="varchar(32)"/>
        <parameter name="Null" value="NO"/>
        <parameter name="Key" value=""/>
        <parameter name="Default" value=""/>
        <parameter name="Extra" value=""/>
      </vendor>
    </column>
    <column name="REP_TAB_UID" type="VARCHAR" size="32" required="true" default="">
      <vendor type="mysql">
        <parameter name="Field" value="REP_TAB_UID"/>
        <parameter name="Type" value="varchar(32)"/>
        <parameter name="Null" value="NO"/>
        <parameter name="Key" value=""/>
        <parameter name="Default" value=""/>
        <parameter name="Extra" value=""/>
      </vendor>
    </column>
    <column name="PMR_STATUS" type="VARCHAR" size="32" required="true" default="">
      <vendor type="mysql">
        <parameter name="Field" value="PMR_STATUS"/>
        <parameter name="Type" value="varchar(32)"/>
        <parameter name="Null" value="NO"/>
        <parameter name="Key" value=""/>
        <parameter name="Default" value=""/>
        <parameter name="Extra" value=""/>
      </vendor>
    </column>
  </table>
  <table name="PM_REPORT_PERMISSIONS">
    <vendor type="mysql">
      <parameter name="Name" value="PM_REPORT_PERMISSIONS"/>
      <parameter name="Engine" value="MyISAM"/>
      <parameter name="Version" value="10"/>
      <parameter name="Row_format" value="Dynamic"/>
      <parameter name="Auto_increment" value=""/>
      <parameter name="Collation" value="utf8_general_ci"/>
      <parameter name="Create_options" value=""/>
      <parameter name="Comment" value="The plugin demo table for pmReports"/>
    </vendor>
    <column name="PMR_UID" type="VARCHAR" size="32" required="true" primaryKey="true" default="">
      <vendor type="mysql">
        <parameter name="Field" value="PMR_UID"/>
        <parameter name="Type" value="varchar(32)"/>
        <parameter name="Null" value="NO"/>
        <parameter name="Key" value="PRI"/>
        <parameter name="Default" value=""/>
        <parameter name="Extra" value=""/>
      </vendor>
    </column>
    <column name="USR_UID" type="VARCHAR" size="32" required="true" primaryKey="true" default="">
      <vendor type="mysql">
        <parameter name="Field" value="USR_UID"/>
        <parameter name="Type" value="varchar(32)"/>
        <parameter name="Null" value="NO"/>
        <parameter name="Key" value="PRI"/>
        <parameter name="Default" value=""/>
        <parameter name="Extra" value=""/>
      </vendor>
    </column>
    <column name="PMRP_TYPE" type="VARCHAR" size="10" required="true" default="">
      <vendor type="mysql">
        <parameter name="Field" value="PMRP_TYPE"/>
        <parameter name="Type" value="varchar(10)"/>
        <parameter name="Null" value="NO"/>
        <parameter name="Key" value=""/>
        <parameter name="Default" value=""/>
        <parameter name="Extra" value=""/>
      </vendor>
    </column>
  </table>
</database>